{"code":0,"msg":"success","data":{"id":"a_5b8641a54a698_QEb2tECv","title":"275-economy-draft-考研英语词汇睡前刷词磨耳朵","desc":"<p><img src=\"http://wechatapppro-1252524126.file.myqcloud.com/appmo2YgYLf9030/image/ueditor/36404200_1535902163.png\" title=\".png\" alt=\"image.png\"/></p>","img_url":"http://wechatapppro-1252524126.file.myqcloud.com/appmo2YgYLf9030/image/bbb6d2e873ec0a65b5d04698c4afc41e.jpg","img_url_compressed":"http://wechatapppro-1252524126.file.myqcloud.com/appmo2YgYLf9030/image/compress/160120bbb6d2e873ec0a65b5d04698c4afc41e.jpg","price":999,"state":0,"comment_count":61,"summary":"","audio_length":458,"start_at":"2018-09-02 22:00:00","created_at":"2018-08-29 14:48:05","is_stop_sell":0,"recycle_bin_state":0,"is_available":1,"audio_url":"http://wechatapppro-1252524126.file.myqcloud.com/appmo2YgYLf9030/audio_compressed/1535525287_39e6187081e34345ce4529fafc48f39a.mp3","payment_type":3,"products":[{"product_id":"p_5a717cb24176d_qUsIkIFD","product_name":"考研英语词汇5500磨耳朵"}],"can_select":0,"view_count":3638,"in_recycle":0,"product_groups":[{"id":"11263","name":"大学考研"}]},"request_params":{"app_id":"appmo2YgYLf9030","data":{"resource_id":"a_5b8641a54a698_QEb2tECv","user_id":"u_5d2efc1648154_OpajJt0AHJ"},"use_type":"11"}}